llm_warehouse/__init__.py
llm_warehouse/observify.py
llm_warehouse/patch_llm.py
llm_warehouse/py.typed
llm_warehouse/query.py
llm_warehouse/transport.py
llm_warehouse-0.1.5.dist-info/licenses/LICENSE
llm_warehouse-0.1.5.dist-info/METADATA
llm_warehouse-0.1.5.dist-info/WHEEL
llm_warehouse-0.1.5.dist-info/top_level.txt
llm_warehouse-0.1.5.dist-info/RECORD
