Metadata-Version: 2.4
Name: llm-warehouse
Version: 0.1.5
Summary: Auto-capture OpenAI and Anthropic LLM calls for warehousing and observability
Author-email: Sinan Ozdemir <sinan.u.ozdemir@gmail.com>
Maintainer-email: Sinan Ozdemir <sinan.u.ozdemir@gmail.com>
License: MIT
Project-URL: Homepage, https://github.com/Agenti-Code/llm-warehousing
Project-URL: Documentation, https://github.com/Agenti-Code/llm-warehousing#readme
Project-URL: Repository, https://github.com/Agenti-Code/llm-warehousing.git
Project-URL: Issues, https://github.com/Agenti-Code/llm-warehousing/issues
Keywords: llm,openai,anthropic,logging,observability,monitoring,warehouse
Classifier: Development Status :: 4 - Beta
Classifier: Intended Audience :: Developers
Classifier: License :: OSI Approved :: MIT License
Classifier: Programming Language :: Python :: 3
Classifier: Programming Language :: Python :: 3.9
Classifier: Programming Language :: Python :: 3.10
Classifier: Programming Language :: Python :: 3.11
Classifier: Programming Language :: Python :: 3.12
Classifier: Topic :: Software Development :: Libraries :: Python Modules
Classifier: Topic :: Scientific/Engineering :: Artificial Intelligence
Classifier: Topic :: System :: Logging
Classifier: Topic :: System :: Monitoring
Requires-Python: >=3.9
License-File: LICENSE
Requires-Dist: wrapt>=1.16.0
Requires-Dist: openai>=1.0.0
Requires-Dist: anthropic>=0.20.0
Requires-Dist: httpx>=0.27
Requires-Dist: requests>=2.31.0
Provides-Extra: dev
Requires-Dist: pytest>=7.0; extra == "dev"
Requires-Dist: pytest-asyncio>=0.21.0; extra == "dev"
Requires-Dist: black>=23.0; extra == "dev"
Requires-Dist: isort>=5.12; extra == "dev"
Requires-Dist: flake8>=6.0; extra == "dev"
Requires-Dist: mypy>=1.0; extra == "dev"
Requires-Dist: build>=0.10.0; extra == "dev"
Requires-Dist: twine>=4.0.0; extra == "dev"
Dynamic: license-file
